calpkg/__init__.py
calpkg/calculator.py
calpkg-0.1.dist-info/METADATA
calpkg-0.1.dist-info/WHEEL
calpkg-0.1.dist-info/top_level.txt
calpkg-0.1.dist-info/RECORD
