Metadata-Version: 2.1
Name: calpkg
Version: 0.1
Summary: calculator package
Home-page: http://discord-peanut.kro.kr
Author: peanut
Author-email: jjun4341@naver.com
License: UNKNOWN
Download-URL: http://discord-peanut.kro.kr
Keywords: calculator
Platform: UNKNOWN
Classifier: Programming Language :: Python :: 3
Classifier: Programming Language :: Python :: 3.2
Classifier: Programming Language :: Python :: 3.3
Classifier: Programming Language :: Python :: 3.4
Classifier: Programming Language :: Python :: 3.5
Classifier: Programming Language :: Python :: 3.6
Classifier: Programming Language :: Python :: 3.7
Requires-Python: >=3
